pypipkg/__init__.py
example_pkg_norbinsh-0.0.2.dist-info/LICENSE
example_pkg_norbinsh-0.0.2.dist-info/METADATA
example_pkg_norbinsh-0.0.2.dist-info/WHEEL
example_pkg_norbinsh-0.0.2.dist-info/top_level.txt
example_pkg_norbinsh-0.0.2.dist-info/RECORD
